journal_crawler/__init__.py
journal_crawler/const.py
journal_crawler/journals/__init__.py
journal_crawler/journals/international_press_crawler.py
journal_crawler/journals/journal_of_singularities_crawler.py
journal_crawler/main.py
journal_crawler/utils.py
journal_crawler-0.0.1.dist-info/LICENSE
journal_crawler-0.0.1.dist-info/WHEEL
journal_crawler-0.0.1.dist-info/METADATA
journal_crawler-0.0.1.dist-info/RECORD
