Metadata-Version: 2.1
Name: journal-crawler
Version: 0.0.1
Summary: provides thesis entities
Home-page: https://gitlab.com/yassu/ythesis
License: Apache-2.0
Keywords: thesis,journal,crawler
Author: yassu
Author-email: yasu0320.dev@gmail.com
Requires-Python: >=3.8,<4.0
Classifier: Development Status :: 3 - Alpha
Classifier: License :: OSI Approved :: Apache Software License
Classifier: Programming Language :: Python
Classifier: Programming Language :: Python :: 3
Classifier: Programming Language :: Python :: 3 :: Only
Classifier: Programming Language :: Python :: 3.8
Classifier: Programming Language :: Python :: 3.9
Requires-Dist: beautifulsoup4 (>=4.9.3,<5.0.0)
Requires-Dist: requests (>=2.25.1,<3.0.0)
Requires-Dist: ythesis (>=0.1.3,<0.2.0)
Project-URL: Repository, https://gitlab.com/yassu/ythesis
